gmaps_playwright_scraper/__init__.py
gmaps_playwright_scraper/config.py
gmaps_playwright_scraper/scraper.py
gmaps_playwright_scraper/utils.py
gmaps_playwright_scraper-1.0.0.dist-info/licenses/LICENSE
gmaps_playwright_scraper-1.0.0.dist-info/METADATA
gmaps_playwright_scraper-1.0.0.dist-info/WHEEL
gmaps_playwright_scraper-1.0.0.dist-info/top_level.txt
gmaps_playwright_scraper-1.0.0.dist-info/RECORD
